prefect_slurm/__init__.py
prefect_slurm/cli.py
prefect_slurm/config.py
prefect_slurm/settings.py
prefect_slurm/worker.py
prefect_slurm-0.1.3.dist-info/LICENSE
prefect_slurm-0.1.3.dist-info/METADATA
prefect_slurm-0.1.3.dist-info/WHEEL
prefect_slurm-0.1.3.dist-info/entry_points.txt
prefect_slurm-0.1.3.dist-info/RECORD
