Metadata-Version: 2.3
Name: prefect-slurm
Version: 0.1.3
Summary: Prefect worker for running flows on a Slurm HPC cluster
License: Apache 2.0
Author: Aleksandar Rajkovic
Author-email: aleksandar@ebi.ac.uk
Requires-Python: >=3.11,<3.14
Classifier: License :: Other/Proprietary License
Classifier: Programming Language :: Python :: 3
Classifier: Programming Language :: Python :: 3.11
Classifier: Programming Language :: Python :: 3.12
Classifier: Programming Language :: Python :: 3.13
Requires-Dist: aiofiles (>=23.0.0)
Requires-Dist: click (>=8.0.0)
Requires-Dist: ebi-slurpy (>=0.1.1,<0.2.0)
Requires-Dist: prefect (>=3.4.13,<4.0.0)
Requires-Dist: pydantic-settings (>=2.10.1,<3.0.0)
